{
	"backtraceGraph" : 
	{
		"commands" : 
		[
			"install"
		],
		"files" : 
		[
			"lib/relic/src/CMakeLists.txt"
		],
		"nodes" : 
		[
			{
				"file" : 0
			},
			{
				"command" : 0,
				"file" : 0,
				"line" : 240,
				"parent" : 0
			}
		]
	},
	"installers" : 
	[
		{
			"backtrace" : 1,
			"component" : "Unspecified",
			"destination" : "lib",
			"paths" : 
			[
				"relic_build/lib/librelic_s.a"
			],
			"targetId" : "relic_s::@90dc6565fe15e8c61978",
			"targetIndex" : 4,
			"type" : "target"
		}
	],
	"paths" : 
	{
		"build" : "relic_build/src",
		"source" : "lib/relic/src"
	}
}
